Workbook

Sheet 开票金额
A1: 项目名称 | B1: 金额 | C1: 税点 | D1: 税额 | E1: 合计
A2: 国际货物运输代理服务 | B2: ='5月人民币账单（已调格式）'!Q16+'5月人民币账单（已调格式）'!R16+'5月人民币账单（已调格式）'!U16+'5月人民币账单（已调格式）'!W16 -> 9859.395 | C2: 免税 | D2: 0 | E2: =B2+D2 -> 9859.395
A3: 国内货物运输代理服务 | B3: ='5月人民币账单（已调格式）'!O16 -> 700.09906 | C3: 0.06 | D3: ='5月人民币账单（已调格式）'!P16 -> 42.005943 | E3: =B3+D3 -> 742.105
A4: 经纪代理服务-报关费 | B4: ='5月人民币账单（已调格式）'!S16 -> 990.56604 | C4: 0.06 | D4: ='5月人民币账单（已调格式）'!T16 -> 59.433962 | E4: =B4+D4 -> 1050
A5: 总额 | B5: =B2+B3+B4 -> 11550.06 | D5: =D2+D3+D4 -> 101.43991 | E5: =E2+E3+E4 -> 11651.5

Sheet 5月人民币账单（已调格式）
C1: 赛诺吉（深圳）国际货运代理有限公司 JTT Logistics Company Limited
A2: 至：广州拓锐科技有限公司（5.11-5.17） | O2: 国内运费 | Q2: 国际运费 | S2: 报关费 | U2: 国际运费
A3: 发货日期 | B3: SO | C3: FBA | D3: 走货渠道 | E3: 仓库代码 | F3: 箱数 | G3: 长(cm) | H3: 宽(cm) | I3: 高(cm) | J3: 计费重合计 | K3: 单价 | L3: 门到港 总单价*0.07/1.06 | M3: 港到港 总单价*0.35 | N3: 港到门 总单价*0.58 | O3: 国内运费 | P3: 国内税点6% | Q3: 国际运费1 | R3: 国际运费2 | S3: 报关费 | T3: 报关税费6% | U3: 清关费 | V3: 税金 | W3: 附加费 | X3: 其他费用 | Y3: 退税损失 | Z3: 币种 | AA3: 总应收(RMB) | AB3: 备注
A4: 46158 | B4: JTT202605000320 | C4: FBA19D4ZZ6L1 | D4: 美国超快线-卡派 | E4: FTW1 | F4: 8 | G4: 42 | H4: 44 | I4: 41 | J4: 117 | L4: =K4*0.07/1.06 -> 0 | M4: =K4*0.35 -> 0 | N4: =K4*0.58 -> 0 | O4: =L4*J4 -> 0 | P4: =O4*0.06 -> 0 | Q4: =M4*J4 -> 0 | R4: =N4*J4 -> 0 | S4: =350/1.06 -> 330.18868 | T4: =S4*0.06 -> 19.811321 | Z4: RMB | AA4: =SUM(O4:Y4) -> 350
A5: 46158 | B5: JTT202605000321 | C5: FBA19D86M1Y6 | D5: 美国超快线-卡派 | E5: VGT2 | F5: 1 | G5: 54 | H5: 33 | I5: 54 | J5: 16 | L5: =K5*0.07/1.06 -> 0 | M5: =K5*0.35 -> 0 | N5: =K5*0.58 -> 0 | O5: =L5*J5 -> 0 | P5: =O5*0.06 -> 0 | Q5: =M5*J5 -> 0 | R5: =N5*J5 -> 0 | Z5: RMB | AA5: =SUM(O5:Y5) -> 0
A6: 46158 | B6: JTT202605000321 | C6: FBA19D4XC89Y | D6: 美国超快线-卡派 | E6: VGT2 | F6: 12 | G6: 54 | H6: 33 | I6: 54 | J6: 192 | L6: =K6*0.07/1.06 -> 0 | M6: =K6*0.35 -> 0 | N6: =K6*0.58 -> 0 | O6: =L6*J6 -> 0 | P6: =O6*0.06 -> 0 | Q6: =M6*J6 -> 0 | R6: =N6*J6 -> 0 | Z6: RMB | AA6: =SUM(O6:Y6) -> 0
A7: 46158 | B7: JTT202605000321 | C7: FBA19D4ZHW94 | D7: 美国超快线-卡派 | E7: VGT2 | F7: 18 | G7: 54 | H7: 33 | I7: 54 | J7: 289 | L7: =K7*0.07/1.06 -> 0 | M7: =K7*0.35 -> 0 | N7: =K7*0.58 -> 0 | O7: =L7*J7 -> 0 | P7: =O7*0.06 -> 0 | Q7: =M7*J7 -> 0 | R7: =N7*J7 -> 0 | Z7: RMB | AA7: =SUM(O7:Y7) -> 0
A8: 46158 | B8: JTT202605000321 | C8: FBA19D4ZL1TP | D8: 美国超快线-卡派 | E8: VGT2 | F8: 10 | G8: 42 | H8: 44 | I8: 41 | J8: 146 | L8: =K8*0.07/1.06 -> 0 | M8: =K8*0.35 -> 0 | N8: =K8*0.58 -> 0 | O8: =L8*J8 -> 0 | P8: =O8*0.06 -> 0 | Q8: =M8*J8 -> 0 | R8: =N8*J8 -> 0 | Z8: RMB | AA8: =SUM(O8:Y8) -> 0
A9: 46158 | B9: JTT202605000324 | C9: FBA19D8FFYK9 | D9: 美国超快线-卡派 | E9: ORF2 | F9: 4 | G9: 43 | H9: 47 | I9: 43 | J9: 65 | L9: =K9*0.07/1.06 -> 0 | M9: =K9*0.35 -> 0 | N9: =K9*0.58 -> 0 | O9: =L9*J9 -> 0 | P9: =O9*0.06 -> 0 | Q9: =M9*J9 -> 0 | R9: =N9*J9 -> 0 | Z9: RMB | AA9: =SUM(O9:Y9) -> 0
A10: 46158 | B10: JTT202605000325 | C10: FBA19D8BK752 | D10: 美国超快线-卡派 | E10: ONT8 | F10: 2 | G10: 44 | H10: 48 | I10: 43 | J10: 32 | L10: =K10*0.07/1.06 -> 0 | M10: =K10*0.35 -> 0 | N10: =K10*0.58 -> 0 | O10: =L10*J10 -> 0 | P10: =O10*0.06 -> 0 | Q10: =M10*J10 -> 0 | R10: =N10*J10 -> 0 | Z10: RMB | AA10: =SUM(O10:Y10) -> 0
A11: 46158 | B11: JTT202605000326 | C11: FBA19D8GG5JD | D11: 美国超快线-卡派 | E11: GYR3 | F11: 3 | G11: 44 | H11: 47 | I11: 43 | J11: 49 | L11: =K11*0.07/1.06 -> 0 | M11: =K11*0.35 -> 0 | N11: =K11*0.58 -> 0 | O11: =L11*J11 -> 0 | P11: =O11*0.06 -> 0 | Q11: =M11*J11 -> 0 | R11: =N11*J11 -> 0 | Z11: RMB | AA11: =SUM(O11:Y11) -> 0
A12: 46158 | B12: JTT202605000322 | C12: FBA19D6207FC | D12: 美转加东超快线-卡派 | E12: YHM1 | F12: 15 | G12: 59 | H12: 47 | I12: 50 | J12: 347 | K12: 13 | L12: =K12*0.07/1.06 -> 0.85849057 | M12: =K12*0.35 -> 4.55 | N12: =K12*0.58 -> 7.54 | O12: =L12*J12 -> 297.89623 | P12: =O12*0.06 -> 17.873774 | Q12: =M12*J12 -> 1578.85 | R12: =N12*J12 -> 2616.38 | S12: =350/1.06 -> 330.18868 | T12: =S12*0.06 -> 19.811321 | Z12: RMB | AA12: =SUM(O12:Y12) -> 4861
A13: 46158 | B13: JTT202605000322 | C13: FBA19D60F19N | D13: 美转加东超快线-卡派 | E13: YHM1 | F13: 15 | G13: 59 | H13: 47 | I13: 50 | J13: 347 | K13: 13 | L13: =K13*0.07/1.06 -> 0.85849057 | M13: =K13*0.35 -> 4.55 | N13: =K13*0.58 -> 7.54 | O13: =L13*J13 -> 297.89623 | P13: =O13*0.06 -> 17.873774 | Q13: =M13*J13 -> 1578.85 | R13: =N13*J13 -> 2616.38 | Z13: RMB | AA13: =SUM(O13:Y13) -> 4511
A14: 46158 | B14: JTT202605000323 | C14: FBA19D4X2VC8 | D14: 美转加西超快线-卡派 | E14: YVR4 | F14: 8 | G14: 42 | H14: 44 | I14: 41 | J14: 117 | K14: 13.5 | L14: =K14*0.07/1.06 -> 0.89150943 | M14: =K14*0.35 -> 4.725 | N14: =K14*0.58 -> 7.83 | O14: =L14*J14 -> 104.3066 | P14: =O14*0.06 -> 6.2583962 | Q14: =M14*J14 -> 552.825 | R14: =N14*J14 -> 916.11 | S14: =350/1.06 -> 330.18868 | T14: =S14*0.06 -> 19.811321 | Z14: RMB | AA14: =SUM(O14:Y14) -> 1929.5
B16: 合计 | F16: =SUM(F4:F15) -> 96 | J16: =SUM(J4:J15) -> 1717 | O16: =SUM(O4:O15) -> 700.09906 | P16: =SUM(P4:P15) -> 42.005943 | Q16: =SUM(Q4:Q15) -> 3710.525 | R16: =SUM(R4:R15) -> 6148.87 | S16: =SUM(S4:S15) -> 990.56604 | T16: =SUM(T4:T15) -> 59.433962 | U16: =SUM(U4:U15) -> 0 | V16: =SUM(V4:V15) -> 0 | ... Y16: =SUM(Y4:Y15) -> 0 | AA16: =SUM(AA4:AA15) -> 11651.5
W17: 合计 | Z17: RMB | AA17: =AA16 -> 11651.5
A18: 以下账户信息为我司唯一合法收款账户，如付款至其他账户我司概不负责!
A19: 对公账户： 账户名：赛诺吉(深圳)国际货运代理有限公司 公司地址：深圳市福田区沙头街道沙嘴社区沙嘴路8号红树华府A栋35层3504、3505、3506 联系电话：0755-82720817 账 号：41009000040015688 开户行：中国农业银行深圳福田保税区支行
A20: 请勿用私人账户付到我司公账，谢谢配合。

Sheet 报价表A
A2: JTT每周报价汇总表
A3: 月份 | B3: 周 | C3: 渠道 | D3: 仓库 | E3: 单价 | F3: 门到港 总单价 | G3: 港到港 总单价 | H3: 港到门 总单价
A4: 5 | B4: 第三周 | C4: 美转加东超快线-卡派 | D4: YHM1 | E4: 13 | F4: =E4*0.07/1.06 -> 0.85849057 | G4: =E4*0.35 -> 4.55 | H4: =E4*0.58 -> 7.54
A5: 5 | B5: 第三周 | C5: 美转加西超快线-卡派 | D5: YVR4 | E5: 13.5 | F5: =E5*0.07/1.06 -> 0.89150943 | G5: =E5*0.35 -> 4.725 | H5: =E5*0.58 -> 7.83
A6: 5 | B6: 第三周 | C6: 美国超快线-卡派 | D6: FTW1 | E6: 12.2 | F6: =E6*0.07/1.06 -> 0.80566038 | G6: =E6*0.35 -> 4.27 | H6: =E6*0.58 -> 7.076
A7: 5 | B7: 第三周 | C7: 美国超快线-卡派 | D7: VGT2 | E7: 10.4 | F7: =E7*0.07/1.06 -> 0.68679245 | G7: =E7*0.35 -> 3.64 | H7: =E7*0.58 -> 6.032
A8: 5 | B8: 第三周 | C8: 美国超快线-卡派 | D8: ORF2 | E8: 13.7 | F8: =E8*0.07/1.06 -> 0.90471698 | G8: =E8*0.35 -> 4.795 | H8: =E8*0.58 -> 7.946
A9: 5 | B9: 第三周 | C9: 美国超快线-卡派 | D9: ONT8 | E9: 9.6 | F9: =E9*0.07/1.06 -> 0.63396226 | G9: =E9*0.35 -> 3.36 | H9: =E9*0.58 -> 5.568
A10: 5 | B10: 第三周 | C10: 美国超快线-卡派 | D10: GYR3 | E10: 10.4 | F10: =E10*0.07/1.06 -> 0.68679245 | G10: =E10*0.35 -> 3.64 | H10: =E10*0.58 -> 6.032
